setup.py
server/__init__.py
server/server.py
server/chat_tests/__init__.py
server/chat_tests/client_tests.py
server/chat_tests/server_tests.py
server/chat_tests/utils_tests.py
server/common/__init__.py
server/common/decos_logging.py
server/common/descriptors.py
server/common/metacls.py
server/common/utils.py
server/doc/__init__.py
server/doc/source/__init__.py
server/doc/source/conf.py
server/logs/__init__.py
server/logs/client_log_config.py
server/logs/server_log_config.py
server/server/__init__.py
server/server/add_user.py
server/server/config_window.py
server/server/core.py
server/server/remove_user.py
server/server/server_db.py
server/server/server_gui.py
server/server/start_window.py
server_messager_proj.egg-info/PKG-INFO
server_messager_proj.egg-info/SOURCES.txt
server_messager_proj.egg-info/dependency_links.txt
server_messager_proj.egg-info/requires.txt
server_messager_proj.egg-info/top_level.txt