Metadata-Version: 1.0
Name: server-messager-proj
Version: 0.8.3
Summary: server_messager_proj
Home-page: UNKNOWN
Author: Vovk Vladislav
Author-email: vovkvladyslav@yandex.ru
License: UNKNOWN
Platform: UNKNOWN
